my_first_c_ext/__init__.py
my_first_c_ext/__main__.py
my_first_c_ext-0.0.0.dist-info/LICENSE.txt
my_first_c_ext-0.0.0.dist-info/METADATA
my_first_c_ext-0.0.0.dist-info/WHEEL
my_first_c_ext-0.0.0.dist-info/top_level.txt
my_first_c_ext-0.0.0.dist-info/RECORD
