Metadata-Version: 2.1
Name: my-first-c-ext
Version: 0.0.0
Summary: my first python project using c
Author-email: Johannes <johannes-programming@posteo.org>
License: The MIT License (MIT)
Classifier: License :: OSI Approved :: MIT License
Classifier: Programming Language :: Python
Classifier: Programming Language :: Python :: 3
Requires-Python: >=3.11
License-File: LICENSE.txt
